MANIFEST.in
setup.py
QEnvPython312.egg-info/PKG-INFO
QEnvPython312.egg-info/SOURCES.txt
QEnvPython312.egg-info/dependency_links.txt
QEnvPython312.egg-info/top_level.txt
QPT_SDK/__init__.py
QPT_SDK/QEnvPython/__init__.py
QPT_SDK/QEnvPython/python312/LICENSE.txt
QPT_SDK/QEnvPython/python312/_asyncio.pyd
QPT_SDK/QEnvPython/python312/_bz2.pyd
QPT_SDK/QEnvPython/python312/_ctypes.pyd
QPT_SDK/QEnvPython/python312/_decimal.pyd
QPT_SDK/QEnvPython/python312/_elementtree.pyd
QPT_SDK/QEnvPython/python312/_hashlib.pyd
QPT_SDK/QEnvPython/python312/_lzma.pyd
QPT_SDK/QEnvPython/python312/_msi.pyd
QPT_SDK/QEnvPython/python312/_multiprocessing.pyd
QPT_SDK/QEnvPython/python312/_overlapped.pyd
QPT_SDK/QEnvPython/python312/_queue.pyd
QPT_SDK/QEnvPython/python312/_socket.pyd
QPT_SDK/QEnvPython/python312/_sqlite3.pyd
QPT_SDK/QEnvPython/python312/_ssl.pyd
QPT_SDK/QEnvPython/python312/_uuid.pyd
QPT_SDK/QEnvPython/python312/_wmi.pyd
QPT_SDK/QEnvPython/python312/_zoneinfo.pyd
QPT_SDK/QEnvPython/python312/libcrypto-3.dll
QPT_SDK/QEnvPython/python312/libffi-8.dll
QPT_SDK/QEnvPython/python312/libssl-3.dll
QPT_SDK/QEnvPython/python312/pyexpat.pyd
QPT_SDK/QEnvPython/python312/python.cat
QPT_SDK/QEnvPython/python312/python.exe
QPT_SDK/QEnvPython/python312/python3.dll
QPT_SDK/QEnvPython/python312/python312._pth
QPT_SDK/QEnvPython/python312/python312.dll
QPT_SDK/QEnvPython/python312/python312.zip
QPT_SDK/QEnvPython/python312/pythonw.exe
QPT_SDK/QEnvPython/python312/select.pyd
QPT_SDK/QEnvPython/python312/sqlite3.dll
QPT_SDK/QEnvPython/python312/unicodedata.pyd
QPT_SDK/QEnvPython/python312/vcruntime140.dll
QPT_SDK/QEnvPython/python312/vcruntime140_1.dll
QPT_SDK/QEnvPython/python312/winsound.pyd
QPT_SDK/QEnvPython/python312/Lib/site-packages/distutils-precedence.pth
QPT_SDK/QEnvPython/python312/Lib/site-packages/_distutils_hack/__init__.py
QPT_SDK/QEnvPython/python312/Lib/site-packages/_distutils_hack/override.py
QPT_SDK/QEnvPython/python312/Lib/site-packages/pip/__init__.py
QPT_SDK/QEnvPython/python312/Lib/site-packages/pip/__main__.py
QPT_SDK/QEnvPython/python312/Lib/site-packages/pip/__pip-runner__.py
QPT_SDK/QEnvPython/python312/Lib/site-packages/pip-23.3.1.dist-info/AUTHORS.txt
QPT_SDK/QEnvPython/python312/Lib/site-packages/pip-23.3.1.dist-info/INSTALLER
QPT_SDK/QEnvPython/python312/Lib/site-packages/pip-23.3.1.dist-info/LICENSE.txt
QPT_SDK/QEnvPython/python312/Lib/site-packages/pip-23.3.1.dist-info/METADATA
QPT_SDK/QEnvPython/python312/Lib/site-packages/pip-23.3.1.dist-info/RECORD
QPT_SDK/QEnvPython/python312/Lib/site-packages/pip-23.3.1.dist-info/REQUESTED
QPT_SDK/QEnvPython/python312/Lib/site-packages/pip-23.3.1.dist-info/WHEEL
QPT_SDK/QEnvPython/python312/Lib/site-packages/pip-23.3.1.dist-info/entry_points.txt
QPT_SDK/QEnvPython/python312/Lib/site-packages/pip-23.3.1.dist-info/top_level.txt
QPT_SDK/QEnvPython/python312/Lib/site-packages/setuptools-68.2.2.dist-info/INSTALLER
QPT_SDK/QEnvPython/python312/Lib/site-packages/setuptools-68.2.2.dist-info/LICENSE
QPT_SDK/QEnvPython/python312/Lib/site-packages/setuptools-68.2.2.dist-info/METADATA
QPT_SDK/QEnvPython/python312/Lib/site-packages/setuptools-68.2.2.dist-info/RECORD
QPT_SDK/QEnvPython/python312/Lib/site-packages/setuptools-68.2.2.dist-info/REQUESTED
QPT_SDK/QEnvPython/python312/Lib/site-packages/setuptools-68.2.2.dist-info/WHEEL
QPT_SDK/QEnvPython/python312/Lib/site-packages/setuptools-68.2.2.dist-info/entry_points.txt
QPT_SDK/QEnvPython/python312/Lib/site-packages/setuptools-68.2.2.dist-info/top_level.txt
QPT_SDK/QEnvPython/python312/Lib/site-packages/wheel-0.41.3.dist-info/INSTALLER
QPT_SDK/QEnvPython/python312/Lib/site-packages/wheel-0.41.3.dist-info/LICENSE.txt
QPT_SDK/QEnvPython/python312/Lib/site-packages/wheel-0.41.3.dist-info/METADATA
QPT_SDK/QEnvPython/python312/Lib/site-packages/wheel-0.41.3.dist-info/RECORD
QPT_SDK/QEnvPython/python312/Lib/site-packages/wheel-0.41.3.dist-info/REQUESTED
QPT_SDK/QEnvPython/python312/Lib/site-packages/wheel-0.41.3.dist-info/WHEEL
QPT_SDK/QEnvPython/python312/Lib/site-packages/wheel-0.41.3.dist-info/entry_points.txt
